slashd/README.md
slashd/__init__.py
slashd/slashd.py
slashd-1.1.0.dist-info/licenses/LICENSE
slashd-1.1.0.dist-info/WHEEL
slashd-1.1.0.dist-info/METADATA
slashd-1.1.0.dist-info/RECORD
