Metadata-Version: 2.4
Name: slashd
Version: 1.1.0
Summary: A Programming Language
Author-email: Chris Knowlson <22knowlson@parmiters.herts.sch.uk>
Classifier: License :: OSI Approved :: MIT License
License-File: LICENSE
Project-URL: Home, https://github.com/JammingJammerIsJammingToJam/slashd
